genkit/py.typed
genkit/plugins/flask/__init__.py
genkit/plugins/flask/handler.py
genkit/plugins/flask/__init__.py
genkit/plugins/flask/handler.py
genkit_plugin_flask-0.4.0.dist-info/METADATA
genkit_plugin_flask-0.4.0.dist-info/WHEEL
genkit_plugin_flask-0.4.0.dist-info/licenses/LICENSE
genkit_plugin_flask-0.4.0.dist-info/RECORD
