Metadata-Version: 2.4
Name: genkit-plugin-flask
Version: 0.4.0
Summary: Genkit Firebase Plugin
Author: Google
License: Apache-2.0
License-File: LICENSE
Classifier: Development Status :: 3 - Alpha
Classifier: Environment :: Console
Classifier: Environment :: Web Environment
Classifier: Intended Audience :: Developers
Classifier: License :: OSI Approved :: Apache Software License
Classifier: Operating System :: OS Independent
Classifier: Programming Language :: Python
Classifier: Programming Language :: Python :: 3 :: Only
Classifier: Programming Language :: Python :: 3.10
Classifier: Programming Language :: Python :: 3.11
Classifier: Programming Language :: Python :: 3.12
Classifier: Programming Language :: Python :: 3.13
Classifier: Topic :: Scientific/Engineering :: Artificial Intelligence
Classifier: Topic :: Software Development :: Libraries
Requires-Python: >=3.10
Requires-Dist: flask
Requires-Dist: genkit
Requires-Dist: genkit-plugin-flask
Requires-Dist: genkit-plugin-google-genai
Requires-Dist: pydantic>=2.10.5
